PyWnews/__init__.py
PyWnews/pynews.py
PyWnews-0.0.1.dist-info/METADATA
PyWnews-0.0.1.dist-info/WHEEL
PyWnews-0.0.1.dist-info/top_level.txt
PyWnews-0.0.1.dist-info/RECORD
