Metadata-Version: 2.1
Name: PyWnews
Version: 0.0.1
Summary: Getting Important World News
Home-page: UNKNOWN
Author: Niranjan Jain
Author-email: <niranjainjain022@gmail.com>
License: UNKNOWN
Keywords: python,worldnews,scrapper
Platform: UNKNOWN
Classifier: Development Status :: 1 - Planning
Classifier: Intended Audience :: Developers
Classifier: Programming Language :: Python :: 3
Classifier: Operating System :: Unix
Classifier: Operating System :: MacOS :: MacOS X
Classifier: Operating System :: Microsoft :: Windows
Requires-Dist: bs4
Requires-Dist: requests
